setup.py
vat_moss/__init__.py
vat_moss/billing_address.py
vat_moss/declared_residence.py
vat_moss/errors.py
vat_moss/exchange_rates.py
vat_moss/geoip2.py
vat_moss/id.py
vat_moss/phone_number.py
vat_moss/rates.py
vat_moss.egg-info/PKG-INFO
vat_moss.egg-info/SOURCES.txt
vat_moss.egg-info/dependency_links.txt
vat_moss.egg-info/top_level.txt