Metadata-Version: 1.1
Name: vat-moss
Version: 0.10.0
Summary: Tools for VAT MOSS and Norway VAT on digital services.
Home-page: https://github.com/wbond/vat_moss-python
Author: wbond
Author-email: will@wbond.net
License: MIT
Keywords: vat
Platform: UNKNOWN
Classifier: Development Status :: 4 - Beta
Classifier: Intended Audience :: Developers
Classifier: License :: OSI Approved :: MIT License
Classifier: Programming Language :: Python :: 2.7
Classifier: Programming Language :: Python :: 3.3
Classifier: Programming Language :: Python :: 3.4
